ipgw/__init__.py
ipgw/dashboard.py
ipgw/ipgw.py
ipgw/test.py
ipgw-1.1.2.dist-info/DESCRIPTION.rst
ipgw-1.1.2.dist-info/METADATA
ipgw-1.1.2.dist-info/RECORD
ipgw-1.1.2.dist-info/WHEEL
ipgw-1.1.2.dist-info/entry_points.txt
ipgw-1.1.2.dist-info/metadata.json
ipgw-1.1.2.dist-info/top_level.txt
