Metadata-Version: 2.0
Name: ipgw
Version: 1.1.2
Summary: NEU IPGW cli tool
Home-page: https://github.com/j178/ipgw
Author: John Jiang
Author-email: nigelchiang@outlook.com
License: MIT
Keywords: internet,cli
Platform: UNKNOWN
Classifier: Development Status :: 3 - Alpha
Classifier: Environment :: Console
Classifier: Environment :: MacOS X
Classifier: Intended Audience :: End Users/Desktop
Classifier: Intended Audience :: System Administrators
Classifier: Topic :: Internet :: WWW/HTTP
Classifier: Natural Language :: Chinese (Simplified)
Classifier: Natural Language :: English
Classifier: License :: OSI Approved :: MIT License
Classifier: Programming Language :: Python :: 3.5
Requires-Dist: requests
